examples/Langroid_QuickStart_OpenAI_Assistants_API.ipynb
examples/Langroid_quick_start.ipynb
examples/README.md
examples/__init__.py
examples/langroid_quick_examples.ipynb
examples/basic/1-agent-3-tools-address-user.py
examples/basic/1-agent-3-tools.py
examples/basic/1d-screen-click.py
examples/basic/2-agent-tools.py
examples/basic/__init__.py
examples/basic/autocorrect.py
examples/basic/chat-2-agent-discuss.py
examples/basic/chat-local-numerical.py
examples/basic/chat-local.py
examples/basic/chat-persist.py
examples/basic/chat-search-assistant-local.py
examples/basic/chat-search-assistant.py
examples/basic/chat-search.py
examples/basic/chat-tool-function.py
examples/basic/chat-tree-structured-simple.py
examples/basic/chat-tree-structured.py
examples/basic/chat-tree.py
examples/basic/chat.py
examples/basic/completion.py
examples/basic/drug-outcomes.py
examples/basic/fn-call-local-numerical.py
examples/basic/fn-call-local-simple.py
examples/basic/intent-classifier.py
examples/basic/multi-agent-return-result.py
examples/basic/multi-agent-round-table.py
examples/basic/multi-agent-triage.py
examples/basic/oai-asst-chat.py
examples/basic/oai-code-chat.py
examples/basic/plan-subtasks.py
examples/basic/text-to-structured.py
examples/basic/tool-custom-handler.py
examples/basic/tool-extract-short-example.py
examples/basic/xml_tool.py
examples/basic/multi-agent-search-critic/__init__.py
examples/basic/multi-agent-search-critic/assistant_agent.py
examples/basic/multi-agent-search-critic/critic_agent.py
examples/basic/multi-agent-search-critic/main.py
examples/basic/multi-agent-search-critic/search_agent.py
examples/basic/multi-agent-search-critic/tools.py
examples/basic/multi-agent-search-critic-no-orch/__init__.py
examples/basic/multi-agent-search-critic-no-orch/assistant_agent.py
examples/basic/multi-agent-search-critic-no-orch/critic_agent.py
examples/basic/multi-agent-search-critic-no-orch/main.py
examples/basic/multi-agent-search-critic-no-orch/search_agent.py
langroid_examples-0.1.25.dist-info/METADATA
langroid_examples-0.1.25.dist-info/WHEEL
langroid_examples-0.1.25.dist-info/entry_points.txt
langroid_examples-0.1.25.dist-info/RECORD
