Metadata-Version: 2.4
Name: langroid-examples
Version: 0.1.25
Summary: Add your description here
Requires-Python: >=3.11
Requires-Dist: ipython>=8.30.0
Requires-Dist: langroid[all]>=0.27.4
Requires-Dist: semver>=3.0.2
